atkit
