Metadata-Version: 1.1
Name: atkit
Version: 0.1.0
Summary: atkit (an Admin Took KIT) provides a suite of tools whose goal is "total knowledge" regarding the python environment and process.
Home-page: https://github.com/stnbu/atkit
Author: Mike Burr
Author-email: mburr@unintuitive.org
License: MIT
Download-URL: https://github.com/stnbu/atkit/archive/master.zip
Keywords: logging,debugging,development,introspection,monkeypatching,hacking,usercustomize
Platform: UNKNOWN
Classifier: Development Status :: 3 - Alpha
Classifier: Intended Audience :: Developers
Classifier: License :: OSI Approved :: MIT License
Classifier: Programming Language :: Python
Classifier: Topic :: Software Development :: Debuggers
Classifier: Topic :: Software Development :: Testing
Classifier: Topic :: Software Development
Classifier: Topic :: System :: Installation/Setup
Classifier: Topic :: System :: Systems Administration
Classifier: Topic :: Utilities
Requires: npconf
Provides: atkit
